README.rst
setup.py
pyval/__init__.py
pyval.egg-info/PKG-INFO
pyval.egg-info/SOURCES.txt
pyval.egg-info/dependency_links.txt
pyval.egg-info/requires.txt
pyval.egg-info/top_level.txt